dataprep_ai/__init__.py
dataprep_ai/core.py
dataprep_ai/explore.py
dataprep_ai-0.1.4.dist-info/METADATA
dataprep_ai-0.1.4.dist-info/WHEEL
dataprep_ai-0.1.4.dist-info/licenses/LICENSE
dataprep_ai-0.1.4.dist-info/RECORD
