Metadata-Version: 2.4
Name: dataprep-ai
Version: 0.1.4
Summary: One-line, opinionated data cleaning for pandas/Polars. Fixes missing values, categories, outliers, and duplicates with transparent logs and a reproducible report.
Project-URL: Homepage, https://github.com/RohitRajdev/dataprep-ai
Project-URL: Documentation, https://github.com/RohitRajdev/dataprep-ai#readme
Project-URL: Issues, https://github.com/RohitRajdev/dataprep-ai/issues
Author-email: Rohit Rajdev <rohit@sandscript.ai>
License: Apache-2.0
License-File: LICENSE
Keywords: data cleaning,data wrangling,pandas,polars,preprocessing
Classifier: License :: OSI Approved :: Apache Software License
Classifier: Operating System :: OS Independent
Classifier: Programming Language :: Python :: 3
Classifier: Programming Language :: Python :: 3 :: Only
Classifier: Programming Language :: Python :: 3.9
Classifier: Programming Language :: Python :: 3.10
Classifier: Programming Language :: Python :: 3.11
Classifier: Programming Language :: Python :: 3.12
Classifier: Topic :: Scientific/Engineering :: Information Analysis
Classifier: Topic :: Software Development :: Libraries :: Python Modules
Requires-Python: <3.13,>=3.9
Requires-Dist: numpy>=1.23
Requires-Dist: pandas>=1.5
Requires-Dist: pyarrow>=10
Requires-Dist: pydantic>=2.6
Requires-Dist: rich>=13.7.0
Requires-Dist: scikit-learn>=1.2
Provides-Extra: app
Requires-Dist: matplotlib>=3.7; extra == 'app'
Requires-Dist: streamlit>=1.35.0; extra == 'app'
Provides-Extra: full
Requires-Dist: matplotlib>=3.7; extra == 'full'
Requires-Dist: polars>=1.0.0; extra == 'full'
Requires-Dist: streamlit>=1.35.0; extra == 'full'
Requires-Dist: ydata-profiling>=4.6; (python_version >= '3.9') and extra == 'full'
